news_recommender_metrics/__init__.py
news_recommender_metrics/RADio/__init__.py
news_recommender_metrics/RADio/calibration.py
news_recommender_metrics/RADio/dart_metrics_abstract.py
news_recommender_metrics/RADio/divergence_metrics.py
news_recommender_metrics/RADio/fragmentation.py
news_recommender_metrics/utils/__init__.py
news_recommender_metrics/utils/probability_mass_function/__init__.py
news_recommender_metrics/utils/probability_mass_function/probability_mass_function.py
news_recommender_metrics/utils/probability_mass_function/rank_aware_probability_mass_function.py
news_recommender_metrics-0.1.4.dist-info/LICENSE
news_recommender_metrics-0.1.4.dist-info/METADATA
news_recommender_metrics-0.1.4.dist-info/WHEEL
news_recommender_metrics-0.1.4.dist-info/top_level.txt
news_recommender_metrics-0.1.4.dist-info/RECORD
