Metadata-Version: 2.1
Name: news-recommender-metrics
Version: 0.1.4
Summary: The implementations of metrics for growing better news recommender systems.
Home-page: https://github.com/morinota/news-recommender-metrics
Author: morinota
Author-email: morinota416@gmail.com
License: UNKNOWN
Platform: UNKNOWN
License-File: LICENSE
